alexgalt_framework/__init__.py
alexgalt_framework/api.py
alexgalt_framework/middleware.py
alexgalt_framework/response.py
alexgalt_framework-0.0.2.dist-info/METADATA
alexgalt_framework-0.0.2.dist-info/WHEEL
alexgalt_framework-0.0.2.dist-info/top_level.txt
alexgalt_framework-0.0.2.dist-info/RECORD
